main.py
setup.py
monlith.egg-info/PKG-INFO
monlith.egg-info/SOURCES.txt
monlith.egg-info/dependency_links.txt
monlith.egg-info/requires.txt
monlith.egg-info/top_level.txt